subtr_actor_py-0.1.11.dist-info/METADATA
subtr_actor_py-0.1.11.dist-info/WHEEL
subtr_actor/__init__.py
subtr_actor/subtr_actor.cpython-310-x86_64-linux-gnu.so
subtr_actor_py-0.1.11.dist-info/RECORD
