Metadata-Version: 2.1
Name: subtr-actor-py
Version: 0.1.11
Summary: Python bindings for the Rocket League replay processing library subtr-actor.
Author: Ivan Malison <ivanmalison@gmail.com>
Author-email: Ivan Malison <ivanmalison@gmail.com>
License: MIT
Requires-Python: >=3.7
Project-URL: Repository, https://github.com/rlrml/subtr-actor
